suvorov/__init__.py
suvorov/__pkginfo__.py
suvorov/ck2path.py
suvorov/conf.py
suvorov/convert.py
suvorov/convert_old.py
suvorov/main.py
suvorov/service.py
suvorov/setup.py
suvorov/suvfile.py
suvorov/utils.py
suvorov-1.0.2.dist-info/LICENSE
suvorov-1.0.2.dist-info/METADATA
suvorov-1.0.2.dist-info/WHEEL
suvorov-1.0.2.dist-info/entry_points.txt
suvorov-1.0.2.dist-info/top_level.txt
suvorov-1.0.2.dist-info/RECORD
