Metadata-Version: 2.1
Name: suvorov
Version: 1.0.2
Summary: Tool to enable a more concise and thematically structured creation of mods for Crusader Kings 2
Home-page: https://github.com/krateng/ck2suite
Author: Johannes Krattenmacher
Author-email: misc@krateng.dev
License: GPLv3
Platform: UNKNOWN
Classifier: Programming Language :: Python :: 3
Classifier: License :: OSI Approved :: GNU General Public License v3 (GPLv3)
Classifier: Operating System :: OS Independent
Requires-Python: >=3.5
Requires-Dist: doreah (>=1.6.1)
Requires-Dist: bierstadt (>=0.2.0)
